<?xml version="1.0" encoding="UTF-8"?>
<flow xmlns="http://www.springframework.org/schema/webflow"
		xmlns:xsi="http://www.w3.org/2001/XMLSchema-instance"
		xsi:schemaLocation="http://www.springframework.org/schema/webflow
		http://www.springframework.org/schema/webflow/spring-webflow-2.4.xsd">
		
	
	<view-state id="signup" view="signUp">
		<transition on="signup" to="success" />
		<transition on="cancel" to="hello" />
	</view-state>
	
	<view-state id="hello" view="hello"></view-state>
	
	<view-state id="success" view="success"></view-state>
	
</flow>